python_mommy/__init__.py
python_mommy/__main__.py
pythonmommy-0.1.3.dist-info/LICENSE
pythonmommy-0.1.3.dist-info/METADATA
pythonmommy-0.1.3.dist-info/WHEEL
pythonmommy-0.1.3.dist-info/top_level.txt
pythonmommy-0.1.3.dist-info/RECORD
