Metadata-Version: 2.1
Name: pythonmommy
Version: 0.1.3
Summary: Mommy's here to support you when running python~ ❤️
Author: googer
Author-email: googer760@gmail.com
Classifier: Programming Language :: Python :: 3
Classifier: License :: OSI Approved :: MIT License
Classifier: Operating System :: OS Independent
Requires-Python: >=3.9
License-File: LICENSE
